RandAlgo_py/__init__.py
RandAlgo_py/fetchequestions.py
RandAlgo_py/main.py
RandAlgo_py/messages.py
RandAlgo_py/user_login.py
RandAlgo_py/user_registration.py
RandAlgo_py-1.0.4.dist-info/LICENSE
RandAlgo_py-1.0.4.dist-info/METADATA
RandAlgo_py-1.0.4.dist-info/WHEEL
RandAlgo_py-1.0.4.dist-info/entry_points.txt
RandAlgo_py-1.0.4.dist-info/top_level.txt
RandAlgo_py-1.0.4.dist-info/RECORD
