Metadata-Version: 2.1
Name: RandAlgo-py
Version: 1.0.4
Summary: A python package to fetche random algorithm questions
Home-page: https://github.com/startng/Forward-RandAlgo-jaynwauche
Author: Nwauche Junior Chimenka
Author-email: juniornwauche@gmail.com
License: MIT
Platform: UNKNOWN
Classifier: License :: OSI Approved :: MIT License
Classifier: Programming Language :: Python :: 3
Classifier: Programming Language :: Python :: 3.8
Requires-Dist: requests
Requires-Dist: bs4
Requires-Dist: lxml
